[
   {
    "title": "Snal-2",
    "year": "22025",
    "category": "Adult",
    "logo":"https://encrypted-tbn0.gstatic.com/images?q=tbn:ANd9GcQG0BEsKJOAVdXXYbpSnaRK2JztH-df4v8aoWTPbYG17d1tjH3CiA&s=10",
    "url":"http://live.mycamtv.com/anal.m3u8"
  },
 {
    "title": "Arab girl",
    "year": "2025",
    "category": "Adult",
    "logo":"https://encrypted-tbn0.gstatic.com/images?q=tbn:ANd9GcQqh01p-4SeDUtTvyX3PkKhg0B2MNSBrq9u0Efzfza040EI_Agi3w&s=10",
    "http://live.mycamtv.com/arab.m3u8"
  },
  {
    "title": "Asian",
    "year": "2025",
    "category": "adult",
    "logo":"https://cdn.staticstack.net/assets/img/r-thumbs/75c02ef-asianbabecams_small.png",
    "url":"http://cdn.adultiptv.net/asian.m3u8"
  }
]
